xxtest0616v1/__init__.py
xxtest0616v1/cli.py
xxtest0616v1/demo.py
xxtest0616v1/http.py
xxtest0616v1/version.py
xxtest0616v1-0.0.0.1.dist-info/LICENSE
xxtest0616v1-0.0.0.1.dist-info/METADATA
xxtest0616v1-0.0.0.1.dist-info/WHEEL
xxtest0616v1-0.0.0.1.dist-info/entry_points.txt
xxtest0616v1-0.0.0.1.dist-info/top_level.txt
xxtest0616v1-0.0.0.1.dist-info/RECORD
