Metadata-Version: 2.1
Name: xxtest0616v1
Version: 0.0.0.1
Summary: A query language for language models.
Home-page: https://lmql.ai
Author: lxx
Author-email: hello@lmql.ai
License: UNKNOWN
Project-URL: Docs, https://docs.lmql.ai
Platform: UNKNOWN
Classifier: Programming Language :: Python :: 3
Classifier: Operating System :: OS Independent
Requires-Python: >=3.10
Requires-Dist: astunparse (==1.6.3)
Requires-Dist: openai
Requires-Dist: termcolor
Requires-Dist: numpy
Requires-Dist: tiktoken
Requires-Dist: psutil
Provides-Extra: hf
Requires-Dist: transformers (>=4.28.1) ; extra == 'hf'
Requires-Dist: accelerate ; extra == 'hf'
